redisemaphore/__init__.py
redisemaphore/async_redis_semaphore.py
redisemaphore/redis_semaphore.py
redisemaphore-0.1.0.dist-info/licenses/LICENSE
redisemaphore-0.1.0.dist-info/METADATA
redisemaphore-0.1.0.dist-info/WHEEL
redisemaphore-0.1.0.dist-info/top_level.txt
redisemaphore-0.1.0.dist-info/RECORD
