Metadata-Version: 2.4
Name: redisemaphore
Version: 0.1.0
Summary: Add your description here
Requires-Python: >=3.12
License-File: LICENSE
Requires-Dist: redis>=6.2.0
Dynamic: license-file
